{
	"name": "ObjectBank",
	"layers": [
		{
			"name": "Layer 0",
			"overriden": 0,
			"instances": [
				{
					"type": "Player",
					"properties": {
						"initially-visible": true,
						"initial-animation": "Idle_Down",
						"initial-frame": 0,
						"enable-collisions": true,
						"live-preview": false
					},
					"uid": 57,
					"instanceVariables": {
						"Walking": false,
						"Direction": "Down"
					},
					"behaviors": {
						"ScrollTo": {
							"properties": {
								"enabled": true
							}
						},
						"Flash": {
							"properties": {}
						},
						"Timer": {
							"properties": {}
						}
					},
					"world": {
						"x": 69,
						"y": 50,
						"width": 20.181984540673895,
						"height": 23.065125189341593,
						"originX": 0.5,
						"originY": 0.4375,
						"color": [
							1,
							1,
							1,
							1
						],
						"angle": 6.277535649776002,
						"zElevation": 0
					}
				},
				{
					"type": "Player_Base",
					"properties": {
						"initially-visible": true,
						"initial-animation": "Animation 1",
						"initial-frame": 0,
						"enable-collisions": true,
						"live-preview": false
					},
					"uid": 490,
					"instanceVariables": {},
					"behaviors": {
						"8Direction": {
							"properties": {
								"max-speed": 200,
								"acceleration": 600,
								"deceleration": 500,
								"directions": "dir-8",
								"set-angle": "smooth",
								"default-controls": true,
								"enabled": true
							}
						}
					},
					"world": {
						"x": 37,
						"y": 51,
						"width": 17.4928556845359,
						"height": 17.4928556845359,
						"originX": 0.5,
						"originY": 0.5,
						"color": [
							1,
							1,
							1,
							1
						],
						"angle": 0,
						"zElevation": 0
					}
				},
				{
					"type": "Fire",
					"properties": {
						"initially-visible": true,
						"initial-animation": "Flame",
						"initial-frame": 0,
						"enable-collisions": true,
						"live-preview": false
					},
					"uid": 497,
					"instanceVariables": {},
					"behaviors": {
						"Solid": {
							"properties": {
								"enabled": true,
								"tags": ""
							}
						}
					},
					"world": {
						"x": 208,
						"y": 49,
						"width": 64,
						"height": 64,
						"originX": 0.5,
						"originY": 0.5,
						"color": [
							1,
							1,
							1,
							1
						],
						"angle": 0,
						"zElevation": 0
					}
				},
				{
					"type": "OpenGuide",
					"properties": {
						"type": "button",
						"text": "Field Guide",
						"tooltip": "",
						"initially-visible": true,
						"enabled": true,
						"auto-font-size": true,
						"checked": false,
						"id": ""
					},
					"uid": 500,
					"instanceVariables": {},
					"behaviors": {
						"Anchor": {
							"properties": {
								"left-edge": "window-left",
								"top-edge": "window-top",
								"right-edge": "none",
								"bottom-edge": "none",
								"enabled": true
							}
						}
					},
					"world": {
						"x": 252,
						"y": 41,
						"width": 96,
						"height": 31,
						"originX": 0,
						"originY": 0,
						"color": [
							1,
							1,
							1,
							1
						]
					}
				},
				{
					"type": "SettingsButton",
					"properties": {
						"type": "button",
						"text": "Settings",
						"tooltip": "",
						"initially-visible": true,
						"enabled": true,
						"auto-font-size": true,
						"checked": false,
						"id": ""
					},
					"uid": 502,
					"instanceVariables": {},
					"behaviors": {
						"Anchor": {
							"properties": {
								"left-edge": "window-left",
								"top-edge": "window-top",
								"right-edge": "none",
								"bottom-edge": "none",
								"enabled": true
							}
						}
					},
					"world": {
						"x": 367,
						"y": 41,
						"width": 72,
						"height": 24,
						"originX": 0,
						"originY": 0,
						"color": [
							1,
							1,
							1,
							1
						]
					}
				},
				{
					"type": "WaterPrompt",
					"properties": {
						"text": "It is very important to stay hydrated in a survival situation, so you should find some water as soon as possible. Check out the field guide for more information on water sources.",
						"enable-bbcode": true,
						"font": "Arial",
						"size": 12,
						"line-height": 0,
						"bold": false,
						"italic": false,
						"color": [
							0,
							0,
							0,
							1
						],
						"horizontal-alignment": "left",
						"vertical-alignment": "top",
						"wrapping": "word",
						"initially-visible": true,
						"origin": "top-left"
					},
					"uid": 505,
					"instanceVariables": {},
					"behaviors": {},
					"world": {
						"x": 693,
						"y": 16,
						"width": 252.98221281347037,
						"height": 131.5174404457249,
						"originX": 0,
						"originY": 0,
						"color": [
							1,
							1,
							1,
							1
						],
						"angle": 0,
						"zElevation": 0
					}
				},
				{
					"type": "RunningWater",
					"properties": {
						"initially-visible": true,
						"initial-animation": "Running Water",
						"initial-frame": 0,
						"enable-collisions": true,
						"live-preview": false
					},
					"uid": 503,
					"instanceVariables": {
						"WaterCount": 0
					},
					"behaviors": {
						"Solid": {
							"properties": {
								"enabled": true,
								"tags": ""
							}
						}
					},
					"world": {
						"x": 85,
						"y": 818,
						"width": 200.03499693803582,
						"height": 100.01749846901791,
						"originX": 0.5,
						"originY": 0.5,
						"color": [
							1,
							1,
							1,
							1
						],
						"angle": 0,
						"zElevation": 0
					}
				},
				{
					"type": "GoodWater",
					"properties": {
						"initially-visible": true,
						"initial-animation": "GoodWaterFull",
						"initial-frame": 0,
						"enable-collisions": true,
						"live-preview": false
					},
					"uid": 511,
					"instanceVariables": {
						"AddHydration": 5
					},
					"behaviors": {
						"Pin": {
							"properties": {
								"destroy": false
							}
						}
					},
					"world": {
						"x": 39.07981451994338,
						"y": 155.0798145199434,
						"width": 16.071360982049324,
						"height": 16.071360982049324,
						"originX": 0.5,
						"originY": 0.5,
						"color": [
							1,
							1,
							1,
							1
						],
						"angle": 0,
						"zElevation": 0
					}
				},
				{
					"type": "BadWater",
					"properties": {
						"initially-visible": true,
						"initial-animation": "BadWaterFull",
						"initial-frame": 0,
						"enable-collisions": true,
						"live-preview": false
					},
					"uid": 512,
					"instanceVariables": {},
					"behaviors": {
						"Pin": {
							"properties": {
								"destroy": false
							}
						}
					},
					"world": {
						"x": 91.42783999663688,
						"y": 153.4278399966369,
						"width": 16.40075322702262,
						"height": 16.40075322702262,
						"originX": 0.5,
						"originY": 0.5,
						"color": [
							1,
							1,
							1,
							1
						],
						"angle": 0,
						"zElevation": 0
					}
				},
				{
					"type": "Timer",
					"properties": {
						"text": "15:00",
						"enable-bbcode": true,
						"font": "Arial",
						"size": 30,
						"line-height": 0,
						"bold": false,
						"italic": false,
						"color": [
							1,
							1,
							1,
							1
						],
						"horizontal-alignment": "left",
						"vertical-alignment": "top",
						"wrapping": "word",
						"initially-visible": true,
						"origin": "top-left"
					},
					"uid": 533,
					"instanceVariables": {
						"Time": 15
					},
					"behaviors": {},
					"world": {
						"x": 1398,
						"y": 358,
						"width": 107,
						"height": 52,
						"originX": 0,
						"originY": 0,
						"color": [
							1,
							1,
							1,
							1
						],
						"angle": 0,
						"zElevation": 0
					}
				},
				{
					"type": "WaterSources",
					"properties": {
						"text": "Looks like you found a good source of water, great job! Before you drink your water, make sure you check the field guide for some important tips on how to make sure your water is safe to drink.",
						"enable-bbcode": true,
						"font": "Arial",
						"size": 12,
						"line-height": 0,
						"bold": false,
						"italic": false,
						"color": [
							0,
							0,
							0,
							1
						],
						"horizontal-alignment": "left",
						"vertical-alignment": "top",
						"wrapping": "word",
						"initially-visible": true,
						"origin": "top-left"
					},
					"uid": 292,
					"instanceVariables": {},
					"behaviors": {},
					"world": {
						"x": 696,
						"y": 207,
						"width": 288.2522260007588,
						"height": 122.39281024635393,
						"originX": 0,
						"originY": 0,
						"color": [
							1,
							1,
							1,
							1
						],
						"angle": 0,
						"zElevation": 0
					}
				},
				{
					"type": "FireStartText",
					"properties": {
						"text": "It's important to start a fire before dark. Look in the field guide for some tips on how to collect wood and start a fire.",
						"enable-bbcode": true,
						"font": "Arial",
						"size": 12,
						"line-height": 0,
						"bold": false,
						"italic": false,
						"color": [
							0,
							0,
							0,
							1
						],
						"horizontal-alignment": "left",
						"vertical-alignment": "top",
						"wrapping": "word",
						"initially-visible": true,
						"origin": "top-left"
					},
					"uid": 506,
					"instanceVariables": {},
					"behaviors": {},
					"world": {
						"x": 688,
						"y": 347,
						"width": 252,
						"height": 107,
						"originX": 0,
						"originY": 0,
						"color": [
							1,
							1,
							1,
							1
						],
						"angle": 0,
						"zElevation": 0
					}
				},
				{
					"type": "Text8",
					"properties": {
						"text": "Now that you're done boiling your water, it is time to safely put out your campfire. Check the field guide for tips on how to put out a fire safely without wasting resources.",
						"enable-bbcode": true,
						"font": "Arial",
						"size": 12,
						"line-height": 0,
						"bold": false,
						"italic": false,
						"color": [
							0,
							0,
							0,
							1
						],
						"horizontal-alignment": "left",
						"vertical-alignment": "top",
						"wrapping": "word",
						"initially-visible": true,
						"origin": "top-left"
					},
					"uid": 507,
					"instanceVariables": {},
					"behaviors": {},
					"world": {
						"x": 702,
						"y": 478,
						"width": 252,
						"height": 129,
						"originX": 0,
						"originY": 0,
						"color": [
							1,
							1,
							1,
							1
						],
						"angle": 0,
						"zElevation": 0
					}
				},
				{
					"type": "Text9",
					"properties": {
						"text": "Now that you're hydrated, you have some time to look for something to eat. Check your field guide for some tips on foraging for food. ",
						"enable-bbcode": true,
						"font": "Arial",
						"size": 12,
						"line-height": 0,
						"bold": false,
						"italic": false,
						"color": [
							0,
							0,
							0,
							1
						],
						"horizontal-alignment": "left",
						"vertical-alignment": "top",
						"wrapping": "word",
						"initially-visible": true,
						"origin": "top-left"
					},
					"uid": 508,
					"instanceVariables": {},
					"behaviors": {},
					"world": {
						"x": 335,
						"y": 256,
						"width": 250,
						"height": 110,
						"originX": 0,
						"originY": 0,
						"color": [
							1,
							1,
							1,
							1
						],
						"angle": 0,
						"zElevation": 0
					}
				},
				{
					"type": "Text10",
					"properties": {
						"text": "Congratulations on surviving your first day in the wilderness!",
						"enable-bbcode": true,
						"font": "Arial",
						"size": 12,
						"line-height": 0,
						"bold": false,
						"italic": false,
						"color": [
							0,
							0,
							0,
							1
						],
						"horizontal-alignment": "left",
						"vertical-alignment": "top",
						"wrapping": "word",
						"initially-visible": true,
						"origin": "top-left"
					},
					"uid": 509,
					"instanceVariables": {},
					"behaviors": {},
					"world": {
						"x": 308,
						"y": 373,
						"width": 250,
						"height": 45.16635916254486,
						"originX": 0,
						"originY": 0,
						"color": [
							1,
							1,
							1,
							1
						],
						"angle": 0,
						"zElevation": 0
					}
				},
				{
					"type": "StandingWater",
					"properties": {
						"initially-visible": true,
						"initial-animation": "Animation 1",
						"initial-frame": 0,
						"enable-collisions": true,
						"live-preview": false
					},
					"uid": 510,
					"instanceVariables": {},
					"behaviors": {
						"Solid": {
							"properties": {
								"enabled": true,
								"tags": ""
							}
						}
					},
					"world": {
						"x": 52,
						"y": 471,
						"width": 79.80929651064348,
						"height": 79.38924758164009,
						"originX": -0.39473684210526316,
						"originY": 2.0264550264550265,
						"color": [
							1,
							1,
							1,
							1
						],
						"angle": 0,
						"zElevation": 0
					}
				},
				{
					"type": "GoodWood",
					"properties": {
						"initially-visible": true,
						"initial-animation": "Animation 1",
						"initial-frame": 0,
						"enable-collisions": true,
						"live-preview": false
					},
					"uid": 529,
					"instanceVariables": {},
					"behaviors": {
						"Pin": {
							"properties": {
								"destroy": false
							}
						}
					},
					"world": {
						"x": 233,
						"y": 162,
						"width": 26.97328764712134,
						"height": 33.35127411682235,
						"originX": 0.45454545454545453,
						"originY": 0.5,
						"color": [
							1,
							1,
							1,
							1
						],
						"angle": 0,
						"zElevation": 0
					}
				},
				{
					"type": "BadWood",
					"properties": {
						"initially-visible": true,
						"initial-animation": "Animation 1",
						"initial-frame": 0,
						"enable-collisions": true,
						"live-preview": false
					},
					"uid": 531,
					"instanceVariables": {},
					"behaviors": {
						"Pin": {
							"properties": {
								"destroy": false
							}
						}
					},
					"world": {
						"x": 171,
						"y": 159,
						"width": 29.494364118207283,
						"height": 35.628267506021146,
						"originX": 0.45454545454545453,
						"originY": 0.5,
						"color": [
							1,
							1,
							1,
							1
						],
						"angle": 0,
						"zElevation": 0
					}
				},
				{
					"type": "Text6",
					"properties": {
						"text": "This looks like a good place to build a fire. Stand here to start a fire using the technique from the field guide.",
						"enable-bbcode": true,
						"font": "Arial",
						"size": 12,
						"line-height": 0,
						"bold": false,
						"italic": false,
						"color": [
							0,
							0,
							0,
							1
						],
						"horizontal-alignment": "left",
						"vertical-alignment": "top",
						"wrapping": "word",
						"initially-visible": true,
						"origin": "top-left"
					},
					"uid": 547,
					"instanceVariables": {},
					"behaviors": {},
					"world": {
						"x": 423,
						"y": 483,
						"width": 200,
						"height": 121,
						"originX": 0,
						"originY": 0,
						"color": [
							1,
							1,
							1,
							1
						],
						"angle": 0,
						"zElevation": 0
					}
				},
				{
					"type": "Text7",
					"properties": {
						"text": "Great Job! You started a fire!",
						"enable-bbcode": true,
						"font": "Arial",
						"size": 12,
						"line-height": 0,
						"bold": false,
						"italic": false,
						"color": [
							0,
							0,
							0,
							1
						],
						"horizontal-alignment": "left",
						"vertical-alignment": "top",
						"wrapping": "word",
						"initially-visible": true,
						"origin": "top-left"
					},
					"uid": 515,
					"instanceVariables": {},
					"behaviors": {},
					"world": {
						"x": 193,
						"y": 494,
						"width": 200,
						"height": 62,
						"originX": 0,
						"originY": 0,
						"color": [
							1,
							1,
							1,
							1
						],
						"angle": 0,
						"zElevation": 0
					}
				}
			],
			"sid": 655590328146873,
			"effectTypes": [],
			"isInitiallyVisible": true,
			"color": [
				1,
				1,
				1,
				1
			],
			"backgroundColor": [
				1,
				1,
				1,
				1
			],
			"isTransparent": true,
			"parallaxX": 1,
			"parallaxY": 1,
			"scaleRate": 1,
			"forceOwnTexture": false,
			"useRenderCells": false,
			"blendMode": "normal",
			"global": false
		}
	],
	"sid": 154327177812791,
	"nonworld-instances": [],
	"effectTypes": [],
	"width": 1708,
	"height": 960,
	"unboundedScrolling": false,
	"eventSheet": "eMain"
}